backendspawner/__init__.py
backendspawner/api_events.py
backendspawner/backendspawner.py
backendspawner/eventspawner.py
jupyterhub_backendspawner-0.4.0.dist-info/LICENSE
jupyterhub_backendspawner-0.4.0.dist-info/METADATA
jupyterhub_backendspawner-0.4.0.dist-info/WHEEL
jupyterhub_backendspawner-0.4.0.dist-info/top_level.txt
jupyterhub_backendspawner-0.4.0.dist-info/RECORD
