Metadata-Version: 2.1
Name: jupyterhub-backendspawner
Version: 0.4.0
Summary: JupyterHub Spawner to spawn on different systems.
Home-page: https://github.com/kreuzert/jupyterhub-backendspawner
Author: Tim Kreuzer
Author-email: t.kreuzer@fz-juelich.de
License: 3-BSD
Requires-Python: >=3.9
License-File: LICENSE
Requires-Dist: jupyterhub
Requires-Dist: traitlets
